LICENSE
README.md
setup.py
weshort/__init__.py
weshort/base.py
weshort/clients.py
weshort/exception.py
weshort/version.py
weshort.egg-info/PKG-INFO
weshort.egg-info/SOURCES.txt
weshort.egg-info/dependency_links.txt
weshort.egg-info/not-zip-safe
weshort.egg-info/requires.txt
weshort.egg-info/top_level.txt
weshort/methods/__init__.py
weshort/methods/payment/__init__.py
weshort/methods/payment/checkTransaction.py
weshort/methods/payment/createPayment.py
weshort/methods/payment/getPayment.py
weshort/methods/shorts/__init__.py
weshort/methods/shorts/createShortUrl.py
weshort/methods/shorts/deleteShortUrl.py
weshort/methods/shorts/getShortUrl.py
weshort/methods/withdraw/__init__.py
weshort/methods/withdraw/getWithdraw.py
weshort/methods/withdraw/reqWithdraw.py
weshort/types/__init__.py
weshort/types/getme.py
weshort/types/payment.py
weshort/types/response.py
weshort/types/shorts.py
weshort/types/withdraw.py