Metadata-Version: 2.1
Name: weshort
Version: 1.0.1
Summary: WeShort is Shortener URL and Asynchronous API in Python
Home-page: https://github.com/AyiinXd/pyweshort
Download-URL: https://github.com/AyiinXd/pyweshort/releases/latest
Author: AyiinXd
Author-email: ayiin@gotgel.org
License: LGPLv3
Project-URL: Tracker, https://github.com/AyiinXd/pyweshort/issues
Project-URL: Community, https://t.me/AyiinProjects
Project-URL: Source, https://github.com/AyiinXd/pyweshort
Keywords: api scrapper library python shortener shortlink shorturl url
Classifier: Development Status :: 5 - Production/Stable
Classifier: Intended Audience :: Developers
Classifier: Natural Language :: English
Classifier: License :: OSI Approved :: MIT License
Classifier: Operating System :: OS Independent
Classifier: Programming Language :: Python
Classifier: Programming Language :: Python :: 3
Classifier: Programming Language :: Python :: 3.7
Classifier: Programming Language :: Python :: 3.8
Classifier: Programming Language :: Python :: 3.9
Classifier: Programming Language :: Python :: 3.10
Classifier: Programming Language :: Python :: 3.11
Classifier: Programming Language :: Python :: 3.12
Classifier: Topic :: Internet
Classifier: Topic :: Communications
Classifier: Topic :: Communications :: Chat
Classifier: Topic :: Software Development :: Libraries
Classifier: Topic :: Software Development :: Libraries :: Python Modules
Requires-Python: ~=3.7
License-File: LICENSE
